{
	"configurations" : 
	[
		{
			"directories" : 
			[
				{
					"build" : ".",
					"hasInstallRule" : true,
					"jsonFile" : "directory-.-Release-6cef8484828249814e49.json",
					"minimumCMakeVersion" : 
					{
						"string" : "3.20"
					},
					"projectIndex" : 0,
					"source" : ".",
					"targetIndexes" : 
					[
						0,
						1
					]
				}
			],
			"name" : "Release",
			"projects" : 
			[
				{
					"directoryIndexes" : 
					[
						0
					],
					"name" : "husarion_ugv",
					"targetIndexes" : 
					[
						0,
						1
					]
				}
			],
			"targets" : 
			[
				{
					"directoryIndex" : 0,
					"id" : "husarion_ugv_uninstall::@6890427a1f51a3e7e1df",
					"jsonFile" : "target-husarion_ugv_uninstall-Release-12eba2d2494519f40663.json",
					"name" : "husarion_ugv_uninstall",
					"projectIndex" : 0
				},
				{
					"directoryIndex" : 0,
					"id" : "uninstall::@6890427a1f51a3e7e1df",
					"jsonFile" : "target-uninstall-Release-7611ec32a63154da6090.json",
					"name" : "uninstall",
					"projectIndex" : 0
				}
			]
		}
	],
	"kind" : "codemodel",
	"paths" : 
	{
		"build" : "/home/nfl/husarion_rusak/src/build/husarion_ugv",
		"source" : "/home/nfl/husarion_rusak/src/husarion_ugv_ros/husarion_ugv"
	},
	"version" : 
	{
		"major" : 2,
		"minor" : 6
	}
}
